MANIFEST.in
README.rst
RELEASE-VERSION
deterministic_dingus.py
setup.py
version.py
deterministic_dingus.egg-info/PKG-INFO
deterministic_dingus.egg-info/SOURCES.txt
deterministic_dingus.egg-info/dependency_links.txt
deterministic_dingus.egg-info/requires.txt
deterministic_dingus.egg-info/top_level.txt