Metadata-Version: 1.0
Name: deterministic-dingus
Version: 0.0.5
Summary: A handy extension of the dingus record and assert library
Home-page: https://github.com/allancaffee/deterministic-dingus
Author: Allan Caffee
Author-email: allan.caffee@gmail.com
License: BSD
Keywords: testing test mocking mock double stub fake record assert
Platform: UNKNOWN
Classifier: Development Status :: 2 - Pre-Alpha
Classifier: Intended Audience :: Developers
Classifier: License :: OSI Approved :: MIT License
Classifier: Operating System :: OS Independent
Classifier: Programming Language :: Python
Classifier: Topic :: Software Development :: Testing
